cblearn/__init__.py
cblearn/_version.py
cblearn/cluster/__init__.py
cblearn/cluster/_comparison_hc.py
cblearn/cluster/tests/__init__.py
cblearn/cluster/tests/test_comparison_hc.py
cblearn/datasets/__init__.py
cblearn/datasets/_base.py
cblearn/datasets/_car_similarity.py
cblearn/datasets/_datatypes.py
cblearn/datasets/_food_similarity.py
cblearn/datasets/_imagenet_similarity.py
cblearn/datasets/_linear_subspace.py
cblearn/datasets/_material_similarity.py
cblearn/datasets/_musician_similarity.py
cblearn/datasets/_nature_vogue_similarity.py
cblearn/datasets/_similarity_matrix.py
cblearn/datasets/_things_similarity.py
cblearn/datasets/_triplet_indices.py
cblearn/datasets/_triplet_response.py
cblearn/datasets/_triplet_simulation.py
cblearn/datasets/data/musician_names.txt
cblearn/datasets/descr/car_similarity.rst
cblearn/datasets/descr/food_similarity.rst
cblearn/datasets/descr/imagenet_similarity.rst
cblearn/datasets/descr/material_similarity.rst
cblearn/datasets/descr/musician_similarity.rst
cblearn/datasets/descr/nature_vogue_similarity.rst
cblearn/datasets/descr/similarity_matrix.rst
cblearn/datasets/descr/things_similarity.rst
cblearn/datasets/tests/__init__.py
cblearn/datasets/tests/test_food_similarity.py
cblearn/datasets/tests/test_linear_subspace.py
cblearn/datasets/tests/test_musician_similarity.py
cblearn/datasets/tests/test_triplet_indices.py
cblearn/datasets/tests/test_triplet_response.py
cblearn/embedding/__init__.py
cblearn/embedding/_base.py
cblearn/embedding/_ckl.py
cblearn/embedding/_dims.py
cblearn/embedding/_forte.py
cblearn/embedding/_gnmds.py
cblearn/embedding/_mlds.py
cblearn/embedding/_oenn.py
cblearn/embedding/_soe.py
cblearn/embedding/_ste.py
cblearn/embedding/_torch_utils.py
cblearn/embedding/wrapper/__init__.py
cblearn/embedding/wrapper/_mlds.py
cblearn/embedding/wrapper/_r_base.py
cblearn/embedding/wrapper/_soe.py
cblearn/metrics/__init__.py
cblearn/metrics/_procrustes.py
cblearn/metrics/_triplets.py
cblearn/metrics/tests/__init__.py
cblearn-0.3.0.dist-info/LICENSE
cblearn-0.3.0.dist-info/METADATA
cblearn-0.3.0.dist-info/WHEEL
cblearn-0.3.0.dist-info/top_level.txt
cblearn-0.3.0.dist-info/RECORD
