Metadata-Version: 2.1
Name: cblearn
Version: 0.3.0
Summary: Comparison-based Machine Learning in Python.
Home-page: https://github.com/dekuenstle/cblearn
Author: David-Elias Künstle
Author-email: david-elias.kuenstle@uni-tuebingen.de
Classifier: Development Status :: 1 - Planning
Classifier: Environment :: GPU :: NVIDIA CUDA
Classifier: Intended Audience :: Science/Research
Classifier: Intended Audience :: Developers
Classifier: License :: OSI Approved :: MIT License
Classifier: Programming Language :: Python
Classifier: Topic :: Software Development
Classifier: Topic :: Scientific/Engineering
Classifier: Operating System :: Microsoft :: Windows
Classifier: Operating System :: POSIX
Classifier: Operating System :: Unix
Classifier: Operating System :: MacOS
Classifier: Programming Language :: Python :: 3.9
Classifier: Programming Language :: Python :: 3.10
Classifier: Programming Language :: Python :: 3.11
Classifier: Typing :: Typed
Requires-Python: >=3.9
License-File: LICENSE
Requires-Dist: numpy ~=1.26
Requires-Dist: scipy ~=1.13
Requires-Dist: scikit-learn ~=1.5
Requires-Dist: sparse ~=0.15
Requires-Dist: numba >=0.59
Provides-Extra: docs
Requires-Dist: sphinx ~=7.3 ; extra == 'docs'
Requires-Dist: pydata-sphinx-theme ~=0.15 ; extra == 'docs'
Requires-Dist: sphinx-gallery ~=0.16 ; extra == 'docs'
Requires-Dist: matplotlib ~=3.8 ; extra == 'docs'
Provides-Extra: octave_wrapper
Requires-Dist: oct2py ~=5.6 ; extra == 'octave_wrapper'
Provides-Extra: r_wrapper
Requires-Dist: rpy2 ~=3.5 ; extra == 'r_wrapper'
Provides-Extra: tests
Requires-Dist: pytest ~=7.4 ; extra == 'tests'
Requires-Dist: pytest-cov ~=4.1 ; extra == 'tests'
Requires-Dist: pytest-doctestplus ~=1.1 ; extra == 'tests'
Requires-Dist: pytest-remotedata ~=0.4 ; extra == 'tests'
Requires-Dist: flake8 ~=7.0 ; extra == 'tests'
Requires-Dist: mypy ~=1.8 ; extra == 'tests'
Requires-Dist: pandas ~=2.1 ; extra == 'tests'
Requires-Dist: matplotlib ~=3.8 ; extra == 'tests'
Provides-Extra: torch
Requires-Dist: torch ~=2.1 ; extra == 'torch'
